Metadata-Version: 2.1
Name: odoo13-addon-pos-empty-home
Version: 13.0.1.1.0
Summary: Point of Sale - Hide products if no category is selected
Home-page: https://github.com/OCA/pos
Author: La Louve, GRAP, Odoo Community Association (OCA)
Author-email: support@odoo-community.org
License: AGPL-3
Platform: UNKNOWN
Classifier: Programming Language :: Python
Classifier: Framework :: Odoo
Classifier: License :: OSI Approved :: GNU Affero General Public License v3
Requires-Python: >=3.5
Requires-Dist: odoo (<13.1dev,>=13.0a)
